mcp_shell_server/__init__.py
mcp_shell_server/server.py
mcp_shell_server/shell_executor.py
mcp_shell_server/version.py
mcp_shell_server-1.0.3.dist-info/METADATA
mcp_shell_server-1.0.3.dist-info/WHEEL
mcp_shell_server-1.0.3.dist-info/entry_points.txt
mcp_shell_server-1.0.3.dist-info/RECORD
