Metadata-Version: 2.4
Name: mcp-shell-server
Version: 1.0.3
Summary: MCP Shell Server - Execute shell commands via MCP protocol
Author: tumf
License: MIT
Requires-Python: >=3.11
Requires-Dist: asyncio>=3.4.3
Requires-Dist: mcp>=1.1.2
Provides-Extra: dev
Requires-Dist: black>=23.3.0; extra == 'dev'
Requires-Dist: isort>=5.12.0; extra == 'dev'
Requires-Dist: mypy>=1.2.0; extra == 'dev'
Requires-Dist: pre-commit>=3.2.2; extra == 'dev'
Requires-Dist: ruff>=0.0.262; extra == 'dev'
Provides-Extra: test
Requires-Dist: pytest-asyncio>=0.23.0; extra == 'test'
Requires-Dist: pytest-cov>=6.0.0; extra == 'test'
Requires-Dist: pytest-env>=1.1.0; extra == 'test'
Requires-Dist: pytest-mock>=3.12.0; extra == 'test'
Requires-Dist: pytest>=7.4.0; extra == 'test'
